DNAEncoding/__init__.py
DNAEncoding-1.0.1.dist-info/Licence.txt
DNAEncoding-1.0.1.dist-info/METADATA
DNAEncoding-1.0.1.dist-info/WHEEL
DNAEncoding-1.0.1.dist-info/top_level.txt
DNAEncoding-1.0.1.dist-info/RECORD
