Metadata-Version: 2.1
Name: DNAEncoding
Version: 1.0.1
Summary: This will return a list of Sequnces and OneHot Encoded Siganl
Home-page: UNKNOWN
Author: Shujaat Muhammad
Author-email: UNKNOWN
License: UNKNOWN
Platform: UNKNOWN
Requires-Dist: numpy
Requires-Dist: Bio
